MANIFEST.in
README.md
setup.py
stockpyle/__init__.py
stockpyle/_appengine.py
stockpyle/_base.py
stockpyle/_chained.py
stockpyle/_helpers.py
stockpyle/_memcache.py
stockpyle/_procmem.py
stockpyle/_shove.py
stockpyle/_sqlalchemy.py
stockpyle/_threadlocal.py
stockpyle/exceptions.py
stockpyle/stores.py
stockpyle.egg-info/PKG-INFO
stockpyle.egg-info/SOURCES.txt
stockpyle.egg-info/dependency_links.txt
stockpyle.egg-info/requires.txt
stockpyle.egg-info/top_level.txt
stockpyle/ext/__init__.py
stockpyle/ext/sqlalchemy.py