Metadata-Version: 1.1
Name: stockpyle
Version: 0.1.8
Summary: stockpyle allows the creation of write-through storage for object caching and persistence
Home-page: https://github.com/mjpizz/stockpyle
Author: Matt Pizzimenti
Author-email: mjpizz+stockpyle@gmail.com
License: BSD
Platform: UNKNOWN
Classifier: Development Status :: 3 - Alpha
Classifier: Programming Language :: Python
Classifier: License :: OSI Approved :: BSD License
Classifier: Intended Audience :: Developers
Classifier: Operating System :: OS Independent
Classifier: Natural Language :: English
Classifier: Topic :: Software Development
Classifier: Topic :: System :: Distributed Computing
Classifier: Topic :: Software Development :: Object Brokering
Classifier: Topic :: Database :: Front-Ends
